message_sender/__init__.py
message_sender/_version.py
message_sender/discord.py
message_sender/google_chat.py
message_sender/py.typed
message_sender/email/__init__.py
message_sender/email/proton.py
message_sender/email/smtp.py
message_sender-0.3.0.dist-info/METADATA
message_sender-0.3.0.dist-info/WHEEL
message_sender-0.3.0.dist-info/licenses/LICENSE
message_sender-0.3.0.dist-info/RECORD
