Metadata-Version: 2.4
Name: message-sender
Version: 0.3.0
Summary: Sends Messages with different services such as email
Author-email: Paul Sanders <paul@paulsanders.dev>
License: MIT License
License-File: LICENSE
Keywords: async,email,google-chat,messages
Classifier: Development Status :: 4 - Beta
Classifier: Intended Audience :: Developers
Classifier: License :: OSI Approved :: MIT License
Classifier: Operating System :: OS Independent
Classifier: Programming Language :: Python :: 3.11
Classifier: Programming Language :: Python :: 3.12
Classifier: Programming Language :: Python :: 3.13
Classifier: Programming Language :: Python :: 3.14
Classifier: Typing :: Typed
Requires-Python: >=3.11
Requires-Dist: aiosmtplib>=5.0.0
Requires-Dist: httpx>=0.28.1
